<?xml version="1.0" encoding="UTF-8"?>
<spirit:component xmlns:xilinx="http://www.xilinx.com" xmlns:spirit="http://www.spiritconsortium.org/XMLSchema/SPIRIT/1685-2009" xmlns:xsi="http://www.w3.org/2001/XMLSchema-instance">
  <spirit:vendor>xilinx.com</spirit:vendor>
  <spirit:library>user</spirit:library>
  <spirit:name>audio_direct</spirit:name>
  <spirit:version>1.0</spirit:version>
  <spirit:model>
    <spirit:views>
      <spirit:view>
        <spirit:name>xilinx_anylanguagesynthesis</spirit:name>
        <spirit:displayName>Synthesis</spirit:displayName>
        <spirit:envIdentifier>:vivado.xilinx.com:synthesis</spirit:envIdentifier>
        <spirit:language>Verilog</spirit:language>
        <spirit:modelName>audio_direct</spirit:modelName>
        <spirit:fileSetRef>
          <spirit:localName>xilinx_anylanguagesynthesis_view_fileset</spirit:localName>
        </spirit:fileSetRef>
        <spirit:parameters>
          <spirit:parameter>
            <spirit:name>viewChecksum</spirit:name>
            <spirit:value>4a58bcf3</spirit:value>
          </spirit:parameter>
        </spirit:parameters>
      </spirit:view>
      <spirit:view>
        <spirit:name>xilinx_anylanguagebehavioralsimulation</spirit:name>
        <spirit:displayName>Simulation</spirit:displayName>
        <spirit:envIdentifier>:vivado.xilinx.com:simulation</spirit:envIdentifier>
        <spirit:language>Verilog</spirit:language>
        <spirit:modelName>audio_direct</spirit:modelName>
        <spirit:fileSetRef>
          <spirit:localName>xilinx_anylanguagebehavioralsimulation_view_fileset</spirit:localName>
        </spirit:fileSetRef>
        <spirit:parameters>
          <spirit:parameter>
            <spirit:name>viewChecksum</spirit:name>
            <spirit:value>4a58bcf3</spirit:value>
          </spirit:parameter>
        </spirit:parameters>
      </spirit:view>
      <spirit:view>
        <spirit:name>xilinx_xpgui</spirit:name>
        <spirit:displayName>UI Layout</spirit:displayName>
        <spirit:envIdentifier>:vivado.xilinx.com:xgui.ui</spirit:envIdentifier>
        <spirit:fileSetRef>
          <spirit:localName>xilinx_xpgui_view_fileset</spirit:localName>
        </spirit:fileSetRef>
        <spirit:parameters>
          <spirit:parameter>
            <spirit:name>viewChecksum</spirit:name>
            <spirit:value>f64a5dae</spirit:value>
          </spirit:parameter>
        </spirit:parameters>
      </spirit:view>
    </spirit:views>
    <spirit:ports>
      <spirit:port>
        <spirit:name>clk_i</spirit:name>
        <spirit:wire>
          <spirit:direction>in</spirit:direction>
          <spirit:wireTypeDefs>
            <spirit:wireTypeDef>
              <spirit:typeName>wire</spirit:typeName>
              <spirit:viewNameRef>xilinx_anylanguagesynthesis</spirit:viewNameRef>
              <spirit:viewNameRef>xilinx_anylanguagebehavioralsimulation</spirit:viewNameRef>
            </spirit:wireTypeDef>
          </spirit:wireTypeDefs>
        </spirit:wire>
      </spirit:port>
      <spirit:port>
        <spirit:name>en_i</spirit:name>
        <spirit:wire>
          <spirit:direction>in</spirit:direction>
          <spirit:wireTypeDefs>
            <spirit:wireTypeDef>
              <spirit:typeName>wire</spirit:typeName>
              <spirit:viewNameRef>xilinx_anylanguagesynthesis</spirit:viewNameRef>
              <spirit:viewNameRef>xilinx_anylanguagebehavioralsimulation</spirit:viewNameRef>
            </spirit:wireTypeDef>
          </spirit:wireTypeDefs>
        </spirit:wire>
      </spirit:port>
      <spirit:port>
        <spirit:name>pdm_audio_i</spirit:name>
        <spirit:wire>
          <spirit:direction>in</spirit:direction>
          <spirit:wireTypeDefs>
            <spirit:wireTypeDef>
              <spirit:typeName>wire</spirit:typeName>
              <spirit:viewNameRef>xilinx_anylanguagesynthesis</spirit:viewNameRef>
              <spirit:viewNameRef>xilinx_anylanguagebehavioralsimulation</spirit:viewNameRef>
            </spirit:wireTypeDef>
          </spirit:wireTypeDefs>
        </spirit:wire>
      </spirit:port>
      <spirit:port>
        <spirit:name>pdm_m_clk_o</spirit:name>
        <spirit:wire>
          <spirit:direction>out</spirit:direction>
          <spirit:wireTypeDefs>
            <spirit:wireTypeDef>
              <spirit:typeName>wire</spirit:typeName>
              <spirit:viewNameRef>xilinx_anylanguagesynthesis</spirit:viewNameRef>
              <spirit:viewNameRef>xilinx_anylanguagebehavioralsimulation</spirit:viewNameRef>
            </spirit:wireTypeDef>
          </spirit:wireTypeDefs>
        </spirit:wire>
      </spirit:port>
      <spirit:port>
        <spirit:name>pwm_audio_o</spirit:name>
        <spirit:wire>
          <spirit:direction>out</spirit:direction>
          <spirit:wireTypeDefs>
            <spirit:wireTypeDef>
              <spirit:typeName>wire</spirit:typeName>
              <spirit:viewNameRef>xilinx_anylanguagesynthesis</spirit:viewNameRef>
              <spirit:viewNameRef>xilinx_anylanguagebehavioralsimulation</spirit:viewNameRef>
            </spirit:wireTypeDef>
          </spirit:wireTypeDefs>
        </spirit:wire>
      </spirit:port>
      <spirit:port>
        <spirit:name>done_o</spirit:name>
        <spirit:wire>
          <spirit:direction>out</spirit:direction>
          <spirit:wireTypeDefs>
            <spirit:wireTypeDef>
              <spirit:typeName>wire</spirit:typeName>
              <spirit:viewNameRef>xilinx_anylanguagesynthesis</spirit:viewNameRef>
              <spirit:viewNameRef>xilinx_anylanguagebehavioralsimulation</spirit:viewNameRef>
            </spirit:wireTypeDef>
          </spirit:wireTypeDefs>
        </spirit:wire>
      </spirit:port>
      <spirit:port>
        <spirit:name>pwm_audio_shutdown</spirit:name>
        <spirit:wire>
          <spirit:direction>out</spirit:direction>
          <spirit:wireTypeDefs>
            <spirit:wireTypeDef>
              <spirit:typeName>wire</spirit:typeName>
              <spirit:viewNameRef>xilinx_anylanguagesynthesis</spirit:viewNameRef>
              <spirit:viewNameRef>xilinx_anylanguagebehavioralsimulation</spirit:viewNameRef>
            </spirit:wireTypeDef>
          </spirit:wireTypeDefs>
        </spirit:wire>
      </spirit:port>
    </spirit:ports>
  </spirit:model>
  <spirit:fileSets>
    <spirit:fileSet>
      <spirit:name>xilinx_anylanguagesynthesis_view_fileset</spirit:name>
      <spirit:file>
        <spirit:name>src/PdmSer.v</spirit:name>
        <spirit:fileType>verilogSource</spirit:fileType>
      </spirit:file>
      <spirit:file>
        <spirit:name>src/PdmDes.v</spirit:name>
        <spirit:fileType>verilogSource</spirit:fileType>
      </spirit:file>
      <spirit:file>
        <spirit:name>audio_direct.v</spirit:name>
        <spirit:fileType>verilogSource</spirit:fileType>
        <spirit:userFileType>CHECKSUM_69677f9d</spirit:userFileType>
      </spirit:file>
    </spirit:fileSet>
    <spirit:fileSet>
      <spirit:name>xilinx_anylanguagebehavioralsimulation_view_fileset</spirit:name>
      <spirit:file>
        <spirit:name>src/PdmSer.v</spirit:name>
        <spirit:fileType>verilogSource</spirit:fileType>
        <spirit:userFileType>USED_IN_ipstatic</spirit:userFileType>
      </spirit:file>
      <spirit:file>
        <spirit:name>src/PdmDes.v</spirit:name>
        <spirit:fileType>verilogSource</spirit:fileType>
        <spirit:userFileType>USED_IN_ipstatic</spirit:userFileType>
      </spirit:file>
      <spirit:file>
        <spirit:name>audio_direct.v</spirit:name>
        <spirit:fileType>verilogSource</spirit:fileType>
        <spirit:userFileType>USED_IN_ipstatic</spirit:userFileType>
      </spirit:file>
    </spirit:fileSet>
    <spirit:fileSet>
      <spirit:name>xilinx_xpgui_view_fileset</spirit:name>
      <spirit:file>
        <spirit:name>xgui/audio_direct_v1_0.tcl</spirit:name>
        <spirit:fileType>tclSource</spirit:fileType>
        <spirit:userFileType>CHECKSUM_f92e9879</spirit:userFileType>
        <spirit:userFileType>XGUI_VERSION_2</spirit:userFileType>
      </spirit:file>
    </spirit:fileSet>
  </spirit:fileSets>
  <spirit:description>Direct Audio between MIC and Mono Headphone Out</spirit:description>
  <spirit:parameters>
    <spirit:parameter>
      <spirit:name>Component_Name</spirit:name>
      <spirit:value spirit:resolve="user" spirit:id="PARAM_VALUE.Component_Name" spirit:order="1">audio_direct_v1_0</spirit:value>
    </spirit:parameter>
  </spirit:parameters>
  <spirit:vendorExtensions>
    <xilinx:coreExtensions>
      <xilinx:supportedFamilies>
        <xilinx:family xilinx:lifeCycle="Production">zynq</xilinx:family>
      </xilinx:supportedFamilies>
      <xilinx:taxonomies>
        <xilinx:taxonomy>/UserIP</xilinx:taxonomy>
      </xilinx:taxonomies>
      <xilinx:displayName>Audio Direct</xilinx:displayName>
      <xilinx:vendorDisplayName>Xilinx</xilinx:vendorDisplayName>
      <xilinx:vendorURL>http://www.xilinx.com</xilinx:vendorURL>
      <xilinx:coreRevision>3</xilinx:coreRevision>
      <xilinx:coreCreationDateTime>2016-06-24T17:27:19Z</xilinx:coreCreationDateTime>
      <xilinx:tags>
        <xilinx:tag xilinx:name="nopcore"/>
        <xilinx:tag xilinx:name="xilinx.com:user:audio_direct:1.0_ARCHIVE_LOCATION">C:/xup/PYNQ/audio_direct_source</xilinx:tag>
      </xilinx:tags>
    </xilinx:coreExtensions>
    <xilinx:packagingInfo>
      <xilinx:xilinxVersion>2015.4</xilinx:xilinxVersion>
      <xilinx:checksum xilinx:scope="fileGroups" xilinx:value="989a7e78"/>
      <xilinx:checksum xilinx:scope="ports" xilinx:value="0561970a"/>
      <xilinx:checksum xilinx:scope="parameters" xilinx:value="c5dbf8da"/>
    </xilinx:packagingInfo>
  </spirit:vendorExtensions>
</spirit:component>
